chaoshub/__init__.py
chaoshub/cli.py
chaoshub/cli_overload.py
chaoshub/publish.py
chaoshub/settings.py
chaostoolkit_chaoshub-0.1.1.dist-info/DESCRIPTION.rst
chaostoolkit_chaoshub-0.1.1.dist-info/LICENSE.txt
chaostoolkit_chaoshub-0.1.1.dist-info/METADATA
chaostoolkit_chaoshub-0.1.1.dist-info/RECORD
chaostoolkit_chaoshub-0.1.1.dist-info/WHEEL
chaostoolkit_chaoshub-0.1.1.dist-info/entry_points.txt
chaostoolkit_chaoshub-0.1.1.dist-info/metadata.json
chaostoolkit_chaoshub-0.1.1.dist-info/top_level.txt
