Metadata-Version: 1.2
Name: chaostoolkit-chaoshub
Version: 0.1.1
Summary: Chaos Hub plugin for the Chaos Toolkit project
Home-page: http://chaostoolkit.org
Author: chaostoolkit Team
Author-email: contact@chaostoolkit.org
License: Apache License Version 2.0
Platform: UNKNOWN
Classifier: Intended Audience :: Developers
Classifier: License :: Freely Distributable
Classifier: Operating System :: OS Independent
Classifier: License :: OSI Approved :: Apache Software License
Classifier: Programming Language :: Python
Classifier: Programming Language :: Python :: 3
Classifier: Programming Language :: Python :: 3.5
Classifier: Programming Language :: Python :: 3.6
Classifier: Programming Language :: Python :: Implementation
Classifier: Programming Language :: Python :: Implementation :: CPython
Requires-Python: >=3.5.*
